Laboratorio_03/Tabla_2_POS/tabla02.v
module tabla02();

//POS tabla 2

reg A,B,C;
wire w1,w2,w3,w4,w5,w6,w7,w8,out;

	not NOTA(w1,A);
	not NOTB(w2,B);
	not NOTC(w3,C);

	or OR1(w4,A,B,C);
	or OR2(w5,A,w2,C);
	or OR3(w6,A,w2,w3);
	or OR4(w7,w1,B,C);
	or OR5(w8,w1,B,w3);

	and OUT(out,w4,w5,w6,w7,w8);

initial begin;

	$display("A B C | Y");
	$display("---------");
	$monitor("%b %b %b | %b", A, B, C, out);
	A=0;B=0;C=0;
	#1 C=1;
	#1 B=1;C=0;
	#1 C=1;
	#1 A=1;B=0;C=0;
	#1 C=1;
	#1 B=1;C=0;
	#1 C=1;
	#1 $finish;
end

initial 
	begin
		$dumpfile("tabla02_tb.vcd");
		$dumpvars(0,tabla02);
	end


endmodule

Laboratorio_03/Tabla_2_POS/tabla02_tb.vcd
$date
	Fri Jul 31 23:04:02 2020
$end
$version
	Icarus Verilog
$end
$timescale
	1ps
$end
$scope module tabla02 $end
$var wire 1 ! out $end
$var wire 1 " w1 $end
$var wire 1 # w2 $end
$var wire 1 $ w3 $end
$var wire 1 % w4 $end
$var wire 1 & w5 $end
$var wire 1 ' w6 $end
$var wire 1 ( w7 $end
$var wire 1 ) w8 $end
$var reg 1 * A $end
$var reg 1 + B $end
$var reg 1 , C $end
$upscope $end
$enddefinitions $end
#0
$dumpvars
0,
0+
0*
1)
1(
1'
1&
0%
1$
1#
1"
0!
$end
#1
1!
1%
0$
1,
#2
0!
0&
1$
0#
0,
1+
#3
0'
1&
0$
1,
#4
1$
1)
0(
1#
1'
0"
0,
0+
1*
#5
0)
1(
0$
1,
#6
1!
1$
1)
0#
0,
1+
#7
0$
1,
