Laboratorio_5/Module.v


module tabla1_2a1(input wire A, B,C, output wire Y);
					
		assign Y = A ? (B~^C):(B^C);
		
endmodule

module tabla1_4a1(input wire A,B,  C, output wire Y);

		assign Y = A?(B? (C):(~C)):(B?(~C):(C));
		
endmodule 

module tabla1_8a1(input wire A,B,C,output wire Y);
		
		assign Y = A? (B? (C? 1:0):(C? 0:1)): (B? (C? 0:1):(C? 1:0));
		
endmodule

module tabla2_2a1(input wire A, B,C, output wire Y);

		assign Y = A? (B^C):(B~|C);

endmodule

module tabla2_4a1(input wire A,B,C, output wire Y);

		assign Y = A?(B? (~C):(C)):(B?(0):(~C));

endmodule

module tabla2_8a1(input wire A,B,C, output wire Y);
		
		assign Y = A? (B? (C? 0:1):(C? 1:0)):(B? (C? 0:0):(C? 0:1));

endmodule

Laboratorio_5/Module_tb.v
module testbench();

	reg p1,p2,p3,p4,p5,p6,p7,p8,p9,p10,p11,p12,p13,p14,p15,p16,p17,p18;
	wire led1,led2,led3,led4,led5,led6;
	
	tabla1_2a1 T1mux2(p1,p2,p3,led1);
	
	tabla1_4a1 T1mux4(p4,p5,p6,led2);
	
	tabla1_8a1 T1mux8(p7,p8,p9,led3);
	
	tabla2_2a1 T2mux2(p10,p11,p12,led4);
	
	tabla2_4a1 T2mux4(p13,p14,p15,led5);
	
	tabla2_8a1 T2mux8(p16,p17,p18,led6);
 	
	initial begin 
	
	$display("Tabla 1, mux 2:1");
	$display("A B C | Y");
	$display("------|--");
	$monitor("%b %b %b | %b", p1,p2,p3,led1);
	p1=0;p2=0;p3=0;
	#1 p1=0;p2=0;p3=1;
	#1 p1=0;p2=1;p3=0;
	#1 p1=0;p2=1;p3=1;
	#1 p1=1;p2=0;p3=0;
	#1 p1=1;p2=0;p3=1;
	#1 p1=1;p2=1;p3=0;
	#1 p1=1;p2=1;p3=1;
	
	end
	
	initial begin
	
	#20
	$display("\n");
	$display("Tabla 1, mux 4:1");
	$display("A B C | Y");
	$display("------|--");
	$monitor("%b %b %b | %b", p4,p5,p6,led2);
	p4=0;p5=0;p6=0;
	#1 p4=0;p5=0;p6=1;
	#1 p4=0;p5=1;p6=0;
	#1 p4=0;p5=1;p6=1;
	#1 p4=1;p5=0;p6=0;
	#1 p4=1;p5=0;p6=1;
	#1 p4=1;p5=1;p6=0;
	#1 p4=1;p5=1;p6=1;
	
	end
	
	initial begin
	
	#40
	$display("\n");
	$display("Tabla 1, mux 8:1");
	$display("A B C | Y");
	$display("------|--");
	$monitor("%b %b %b | %b", p7,p8,p9,led3);
	p7=0;p8=0;p9=0;
	#1 p7=0;p8=0;p9=1;
	#1 p7=0;p8=1;p9=0;
	#1 p7=0;p8=1;p9=1;
	#1 p7=1;p8=0;p9=0;
	#1 p7=1;p8=0;p9=1;
	#1 p7=1;p8=1;p9=0;
	#1 p7=1;p8=1;p9=1;
	
	end
	
	initial begin
	
	#80
	$display("\n");
	$display("Tabla 2, mux 2:1");
	$display("A B C | Y");
	$display("------|--");
	$monitor("%b %b %b | %b", p10,p11,p12,led4);
	p10=0;p11=0;p12=0;
	#1 p10=0;p11=0;p12=1;
	#1 p10=0;p11=1;p12=0;
	#1 p10=0;p11=1;p12=1;
	#1 p10=1;p11=0;p12=0;
	#1 p10=1;p11=0;p12=1;
	#1 p10=1;p11=1;p12=0;
	#1 p10=1;p11=1;p12=1;
	
	end
	
	initial begin
	
	#100
	$display("\n");
	$display("Tabla 2, mux 4:1");
	$display("A B C | Y");
	$display("------|--");
	$monitor("%b %b %b | %b", p13,p14,p15,led5);
	p13=0;p14=0;p15=0;
	#1 p13=0;p14=0;p15=1;
	#1 p13=0;p14=1;p15=0;
	#1 p13=0;p14=1;p15=1;
	#1 p13=1;p14=0;p15=0;
	#1 p13=1;p14=0;p15=1;
	#1 p13=1;p14=1;p15=0;
	#1 p13=1;p14=1;p15=1;
	
	end
	
	initial begin
	
	#120
	$display("\n");
	$display("Tabla 2, mux 8:1");
	$display("A B C | Y");
	$display("------|--");
	$monitor("%b %b %b | %b", p16,p17,p18,led6);
	p16=0;p17=0;p18=0;
	#1 p16=0;p17=0;p18=1;
	#1 p16=0;p17=1;p18=0;
	#1 p16=0;p17=1;p18=1;
	#1 p16=1;p17=0;p18=0;
	#1 p16=1;p17=0;p18=1;
	#1 p16=1;p17=1;p18=0;
	#1 p16=1;p17=1;p18=1;
	
	end
	
	initial begin
		$dumpfile("Module_tb.vcd");
		$dumpvars(0,testbench);
	
	end
	initial 
	#140 $finish;

endmodule

Laboratorio_5/Module_tb.vcd
$date
	Sun Aug 16 09:03:00 2020
$end
$version
	Icarus Verilog
$end
$timescale
	1ps
$end
$scope module testbench $end
$var wire 1 ! led6 $end
$var wire 1 " led5 $end
$var wire 1 # led4 $end
$var wire 1 $ led3 $end
$var wire 1 % led2 $end
$var wire 1 & led1 $end
$var reg 1 ' p1 $end
$var reg 1 ( p10 $end
$var reg 1 ) p11 $end
$var reg 1 * p12 $end
$var reg 1 + p13 $end
$var reg 1 , p14 $end
$var reg 1 - p15 $end
$var reg 1 . p16 $end
$var reg 1 / p17 $end
$var reg 1 0 p18 $end
$var reg 1 1 p2 $end
$var reg 1 2 p3 $end
$var reg 1 3 p4 $end
$var reg 1 4 p5 $end
$var reg 1 5 p6 $end
$var reg 1 6 p7 $end
$var reg 1 7 p8 $end
$var reg 1 8 p9 $end
$scope module T1mux2 $end
$var wire 1 ' A $end
$var wire 1 1 B $end
$var wire 1 2 C $end
$var wire 1 & Y $end
$upscope $end
$scope module T1mux4 $end
$var wire 1 3 A $end
$var wire 1 4 B $end
$var wire 1 5 C $end
$var wire 1 % Y $end
$upscope $end
$scope module T1mux8 $end
$var wire 1 6 A $end
$var wire 1 7 B $end
$var wire 1 8 C $end
$var wire 1 $ Y $end
$upscope $end
$scope module T2mux2 $end
$var wire 1 ( A $end
$var wire 1 ) B $end
$var wire 1 * C $end
$var wire 1 # Y $end
$upscope $end
$scope module T2mux4 $end
$var wire 1 + A $end
$var wire 1 , B $end
$var wire 1 - C $end
$var wire 1 " Y $end
$upscope $end
$scope module T2mux8 $end
$var wire 1 . A $end
$var wire 1 / B $end
$var wire 1 0 C $end
$var wire 1 ! Y $end
$upscope $end
$upscope $end
$enddefinitions $end
#0
$dumpvars
x8
x7
x6
x5
x4
x3
02
01
x0
x/
x.
x-
x,
x+
x*
x)
x(
0'
0&
x%
x$
x#
x"
x!
$end
#1
1&
12
#2
02
11
#3
0&
12
#4
1&
02
01
1'
#5
0&
12
#6
02
11
#7
1&
12
#20
0%
05
04
03
#21
1%
15
#22
1%
05
14
#23
0%
15
#24
1%
05
04
13
#25
0%
15
#26
05
14
#27
1%
15
#40
0$
08
07
06
#41
1$
18
#42
1$
08
17
#43
0$
18
#44
1$
08
07
16
#45
0$
18
#46
0$
08
17
#47
1$
18
#80
1#
0*
0)
0(
#81
0#
1*
#82
0*
1)
#83
1*
#84
0*
0)
1(
#85
1#
1*
#86
0*
1)
#87
0#
1*
#100
1"
0-
0,
0+
#101
0"
1-
#102
0-
1,
#103
1-
#104
0-
0,
1+
#105
1"
1-
#106
1"
0-
1,
#107
0"
1-
#120
1!
00
0/
0.
#121
0!
10
#122
00
1/
#123
10
#124
0!
00
0/
1.
#125
1!
10
#126
1!
00
1/
#127
0!
10
