Laboratorio_06/Ejercicio_5/FlipFlopD.v
module ffd4(input clk, reset, set, input [1:0]d, output  reg[1:0]q);

always @(posedge clk or posedge reset) 

	if (reset==1) 
		q<=4'b00;
	else if (set==1) q<=4'b01;
		else q<= d;
	
endmodule

Laboratorio_06/Ejercicio_5/FlipFlopD_tb.v

module testbench();

reg clk,reset,set,d;
wire q;

ffd4 U1(clk,reset,set,d,q);

initial begin
	
	$display("clk reset set D | Q");
	$display("----------------|--");
	$monitor("%b  %b   %b    %b | %b",clk,reset,set,d,q);
	end
	
initial begin
	clk=0;
	reset=0;
	set=0;
	d=0000;
	#1 d=0001;
	#1 d=0010;
	#1 d=0101;
	#4 reset =1;
	#4 reset =0;
	#2 set =1;
	#2 set =0;
	#2 reset=1;
	#20
	$finish;
	
end

	always 
		#5 clk= ~clk;
		
initial begin
		
		$dumpfile("FlipFlopD_tb.vcd");
		$dumpvars(0,testbench);
	
	end
	
endmodule

Laboratorio_06/Ejercicio_5/FlipFlopD_tb.vcd
$date
	Sat Sep 05 23:36:49 2020
$end
$version
	Icarus Verilog
$end
$timescale
	1ps
$end
$scope module testbench $end
$var wire 1 ! q $end
$var reg 1 " clk $end
$var reg 1 # d $end
$var reg 1 $ reset $end
$var reg 1 % set $end
$scope module U1 $end
$var wire 1 " clk $end
$var wire 2 & d [1:0] $end
$var wire 1 $ reset $end
$var wire 1 % set $end
$var reg 2 ' q [1:0] $end
$upscope $end
$upscope $end
$enddefinitions $end
#0
$dumpvars
bx '
b0 &
0%
0$
0#
0"
x!
$end
#1
b1 &
1#
#2
b0 &
0#
#3
b1 &
1#
#5
1!
b1 '
1"
#7
0!
b0 '
1$
#10
0"
#11
0$
#13
1%
#15
1!
b1 '
0%
1"
#17
0!
b0 '
1$
