Laboratorio_03/Tabla_4_POS/tabla04.v
module tabla04();

//POS de la tabla 4

reg A,B,C,D;

wire w1,w2,w3,w4,w5,w6,w7,w8,w9,w10,w11,w12,w13,out;

	not NOTA(w1,A);
	not NOTB(w2,B);
	not NOTC(w3,C);
	not NOTD(w4,D);
	
	or OR1(w5,A,B,C,w4);
	or OR2(w6,A,w2,C,D);
	or OR3(w7,A,w2,C,w4);
	or OR4(w8,w1,B,C,w4);
	or OR5(w9,w1,B,w3,w4);
	or OR6(w10,w1,w2,C,D);
	or OR7(w11,w1,w2,C,w4);
	or OR8(w12,w1,w2,w3,D);
	or OR9(w13,w1,w2,w3,w4);
	
	and OUT(out,w5,w6,w7,w8,w9,w10,w11,w12,w13);


initial begin;
	
	$display("A B C D | Y");
	$display("---------");
	$monitor("%b %b %b %b | %b", A, B, C, D, out);
	
	A=0;B=0;C=0;D=0;
	#1 D=1;
	#1 C=1;D=0;
	#1 D=1;
	#1 B=1;C=0;D=0;
	#1 D=1;
	#1 C=1;D=0;
	#1 D=1;
	#1 A=1;B=0;C=0;D=0;
	#1 D=1;
	#1 C=1;D=0;
	#1 D=1;
	#1 B=1;C=0;D=0;
	#1 D=1;
	#1 C=1;D=0;
	#1 D=1;
	#1 $finish;
end
	
initial 
	begin
		$dumpfile("tabla04_tb.vcd");
		$dumpvars(0,tabla04);
	end

endmodule

Laboratorio_03/Tabla_4_POS/tabla04_tb.vcd
$date
	Fri Jul 31 23:02:57 2020
$end
$version
	Icarus Verilog
$end
$timescale
	1ps
$end
$scope module tabla04 $end
$var wire 1 ! out $end
$var wire 1 " w1 $end
$var wire 1 # w10 $end
$var wire 1 $ w11 $end
$var wire 1 % w12 $end
$var wire 1 & w13 $end
$var wire 1 ' w2 $end
$var wire 1 ( w3 $end
$var wire 1 ) w4 $end
$var wire 1 * w5 $end
$var wire 1 + w6 $end
$var wire 1 , w7 $end
$var wire 1 - w8 $end
$var wire 1 . w9 $end
$var reg 1 / A $end
$var reg 1 0 B $end
$var reg 1 1 C $end
$var reg 1 2 D $end
$upscope $end
$enddefinitions $end
#0
$dumpvars
02
01
00
0/
1.
1-
1,
1+
1*
1)
1(
1'
1&
1%
1$
1#
1"
1!
$end
#1
0!
0*
0)
12
#2
1!
1)
1*
0(
02
11
#3
0)
12
#4
0!
1)
1,
0+
1(
0'
02
01
10
#5
0,
1+
0)
12
#6
1!
1)
1,
0(
02
11
#7
0)
12
#8
1!
1)
1(
1.
1-
1'
0"
02
01
00
1/
#9
0!
0-
0)
12
#10
1!
1)
1-
0(
02
11
#11
0!
0.
0)
12
#12
1)
1$
0#
1(
1.
0'
02
01
10
#13
0$
1#
0)
12
#14
0%
1)
1$
0(
02
11
#15
0&
1%
0)
12
