Laboratorio_04/Ejercicio_4/Modulos.v
//EJERCICIO I

//Ecuación Y=(~A*~C)+(A*~B)+(AC), tabla #1
//gateLevel

module tabla_1(input wire A,B,C, output wire Y);

	wire w1,w2,w3,w4,w5,w6;
	
	not (w1,A);
	not (w2,B);
	not (w3,C);
	
	and (w4,w1,w3);
	and (w5,A,w2);
	and (w6,A,C);
	or (Y, w4,w5,w6);
	
endmodule
	
//Ecuación Y =~B, tabla #2
//gateLevel

module tabla_2(input wire B, output wire Y);
	
	not (Y,B);
	
endmodule
	
//Ecuación Y= (~A*~B*~C*~D)+(A*B*~C*~D)+(~A*B*~C*D)+(A*~B*~C*D)+(~A*~B*C*D)+(A*B*C*D)+(~A*B*C*~D)
// + (A*~B*C*~D), tabla #3
//operadores

module tabla_3(input A,B,C,D, output wire Y);

	assign Y=(~A & ~B & ~C & ~D)|(A & B & ~C & ~D)|(~A & B & ~C & D)|(A & ~B & ~C & D)|(~A & ~B & C & D)|(A & B & C & D)|(~A & B & C & ~D)|(A & ~B & C & ~D);
	
endmodule
	
//Ecuación Y=(~B*~D)+(A*C)+(A*B), tabla #4
//operadores

module tabla_4(input wire A,B,C,D, output wire Y);

	assign Y=(~B & ~D)|(A & C)|(A & B);
	
endmodule
	
//////////////////////////////////////////////////////////////////////////////////////////////////////////
	
//EJERCICIO II

//Ecuación Y=(~B*~C*~D)+(A*~C)+(A*~B)+(A*C*~D), tabla #1
//gateLevel

module tabla_1_2 (input wire A,B,C,D, output wire Y);

	wire w1,w2,w3,w4,w5,w6,w7;
	
	not (w1,B);
	not (w2,C);
	not (w3,D);
	
	and (w4,w1,w2,w3);
	and (w5,A,w2);
	and (w6,A,w1);
	and (w7,A,C,w3);
	
	or (Y,w4,w5,w6,w7);
	
endmodule

//Ecuación Y= -B + C, tabla #2
//gateLevel

module tabla_2_2(input wire B,C, output wire Y);

	wire w1;
	
	not (w1,B);
	or(Y,w1,C);
	
endmodule

//Ecuación Y=B+D+C*D, tabla #3
//operadores 

module tabla_3_2(input wire B,C,D, output wire Y);

	assign Y= B | D | (C & D);
	
endmodule

//Ecuación Y= ~C + B, tabla #4
//operadores

module tabla_4_2(input wire B,C, output wire Y);

	assign Y= ~C | B;
	
endmodule

Laboratorio_04/Ejercicio_4/Modulos_tb.v

module testbench();

	reg p1,p2,p3,p4,p5,p6,p7,p8,p9,p10,p11,p12,p13,p14,p15,p16,p17,p18,p19,p20,p21,p22,p23;
	wire led1,led2,led3,led4,led5,led6,led7,led8; 
	
	//Ejercicio #1
	
	tabla_1 T1(p1,p2,p3,led1);
	
	tabla_2 T2(p4,led2);
	
	tabla_3 T3(p5,p6,p7,p8,led3);
	
	tabla_4 T4(p9,p10,p11,p12,led4);
	
	//	Ejercicio #2 
	
	tabla_1_2 T1_2(p13,p14,p15,p16,led5);
	
	tabla_2_2 T2_2(p17,p18,led6);
	
	tabla_3_2 T3_2(p19,p20,p21,led7);
	
	tabla_4_2 T4_2(p22,p23,led8);
	
//////////////////////////////////////////////////////////////////////////////////////////////////
	
//tabla #1
initial begin
		
		$display("A B C | Y");
		$display("------|--");
		$monitor("%b %b %b | %b",p1,p2,p3,led1);
		
		p1=0;p2=0;p3=0;
		#1 p1=0;p2=0;p3=1;
		#1 p1=0;p2=1;p3=0;
		#1 p1=0;p2=1;p3=1;
		#1 p1=1;p2=0;p3=0;
		#1 p1=1;p2=0;p3=1;
		#1 p1=1;p2=1;p3=0;
		#1 p1=1;p2=1;p3=1;
	end
	


//tabla 2
initial begin

		#10
		$display("\n Tabla 2");	
		$display("B | Y");
		$display("--|--");
		$monitor("%b | %b",p4,led2);
		
		p4=0;
		#1 p4=1;		
	
	end
	

//tabla 3
initial begin

		#20
		$display("\n Tabla 3");
		$display("A B C D | Y");
		$display("--------|--");
		$monitor("%b %b %b %b | %b",p5,p6,p7,p8,led3);
		
		p5=0;p6=0;p7=0;p8=0;
		#1 p5=0;p6=0;p7=0;p8=1;
		#1 p5=0;p6=0;p7=1;p8=0;
		#1 p5=0;p6=0;p7=1;p8=1;
		#1 p5=0;p6=1;p7=0;p8=0;
		#1 p5=0;p6=1;p7=0;p8=1;
		#1 p5=0;p6=1;p7=1;p8=0;
		#1 p5=0;p6=1;p7=1;p8=1;
		#1 p5=1;p6=0;p7=0;p8=0;
		#1 p5=1;p6=0;p7=0;p8=1;
		#1 p5=1;p6=0;p7=1;p8=0;
		#1 p5=1;p6=0;p7=1;p8=1;
		#1 p5=1;p6=1;p7=0;p8=0;
		#1 p5=1;p6=1;p7=0;p8=1;
		#1 p5=1;p6=1;p7=1;p8=0;
		#1 p5=1;p6=1;p7=1;p8=1;
		
	end


//tabla 4
initial begin
		#40
		$display("\n Tabla 4");
		$display("A B C D | Y");
		$display("--------|--");
		$monitor("%b %b %b %b | %b",p9,p10,p11,p12,led4);
		
		p9=0;p10=0;p11=0;p12=0;
		#1 p9=0;p10=0;p11=0;p12=1;
		#1 p9=0;p10=0;p11=1;p12=0;
		#1 p9=0;p10=0;p11=1;p12=1;
		#1 p9=0;p10=1;p11=0;p12=0;
		#1 p9=0;p10=1;p11=0;p12=1;
		#1 p9=0;p10=1;p11=1;p12=0;
		#1 p9=0;p10=1;p11=1;p12=1;
		#1 p9=1;p10=0;p11=0;p12=0;
		#1 p9=1;p10=0;p11=0;p12=1;
		#1 p9=1;p10=0;p11=1;p12=0;
		#1 p9=1;p10=0;p11=1;p12=1;
		#1 p9=1;p10=1;p11=0;p12=0;
		#1 p9=1;p10=1;p11=0;p12=1;
		#1 p9=1;p10=1;p11=1;p12=0;
		#1 p9=1;p10=1;p11=1;p12=1;
		
	end
	

//tabla 1_2
initial begin 
		#60
		$display("\n Tabla 1_2");
		$display("A B C D | Y");
		$display("--------|--");
		$monitor("%b %b %b %b | %b",p13,p14,p15,p16,led5);
		
		p13=0;p14=0;p15=0;p16=0;
		#1 p13=0;p14=0;p15=0;p16=1;
		#1 p13=0;p14=0;p15=1;p16=0;
		#1 p13=0;p14=0;p15=1;p16=1;
		#1 p13=0;p14=1;p15=0;p16=0;
		#1 p13=0;p14=1;p15=0;p16=1;
		#1 p13=0;p14=1;p15=1;p16=0;
		#1 p13=0;p14=1;p15=1;p16=1;
		#1 p13=1;p14=0;p15=0;p16=0;
		#1 p13=1;p14=0;p15=0;p16=1;
		#1 p13=1;p14=0;p15=1;p16=0;
		#1 p13=1;p14=0;p15=1;p16=1;
		#1 p13=1;p14=1;p15=0;p16=0;
		#1 p13=1;p14=1;p15=0;p16=1;
		#1 p13=1;p14=1;p15=1;p16=0;
		#1 p13=1;p14=1;p15=1;p16=1;
		
	end
	
//tabla 2_2
initial begin
		#80
		$display("\n Tabla 2_2");
		$display("B C | Y");
		$display("----|--");
		$monitor("%b %b | %b",p17,p18,led6);
		
		p17=0;p18=0;
		#1 p17=0;p18=1;	
		#1 p17=1;p18=0;
		#1 p17=1;p18=1;
		
	end
	
//tabla 3_2
initial begin

		#90
		$display("\n Tabla 3_2");
		$display("B C D | Y");
		$display("------|--");
		$monitor("%b %b %b | %b",p19,p20,p21,led7);
		
		p19=0;p20=0;p21=0;
		#1 p19=0;p20=0;p21=1;
		#1 p19=0;p20=1;p21=0;
		#1 p19=0;p20=1;p21=1;
		#1 p19=1;p20=0;p21=0;
		#1 p19=1;p20=0;p21=1;
		#1 p19=1;p20=1;p21=0;
		#1 p19=1;p20=1;p21=1;
		
	end
	
//tabla 4_2
initial begin
		#100
		$display("\n Tabla 4_2");
		$display("B C | Y");
		$display("----|--");
		$monitor("%b %b | %b",p22,p23,led8);
		
		p22=0;p23=0;
		#1 p22=0;p23=1;	
		#1 p22=1;p23=0;
		#1 p22=1;p23=1;
		
	end
	
	
initial begin
		$dumpfile("Modulos_tb.vcd");
		$dumpvars(0,testbench);
	
	end

initial
	#120 $finish;
endmodule

Laboratorio_04/Ejercicio_4/Modulos_tb.vcd
$date
	Sun Aug 09 18:52:31 2020
$end
$version
	Icarus Verilog
$end
$timescale
	1ps
$end
$scope module testbench $end
$var wire 1 ! led8 $end
$var wire 1 " led7 $end
$var wire 1 # led6 $end
$var wire 1 $ led5 $end
$var wire 1 % led4 $end
$var wire 1 & led3 $end
$var wire 1 ' led2 $end
$var wire 1 ( led1 $end
$var reg 1 ) p1 $end
$var reg 1 * p10 $end
$var reg 1 + p11 $end
$var reg 1 , p12 $end
$var reg 1 - p13 $end
$var reg 1 . p14 $end
$var reg 1 / p15 $end
$var reg 1 0 p16 $end
$var reg 1 1 p17 $end
$var reg 1 2 p18 $end
$var reg 1 3 p19 $end
$var reg 1 4 p2 $end
$var reg 1 5 p20 $end
$var reg 1 6 p21 $end
$var reg 1 7 p22 $end
$var reg 1 8 p23 $end
$var reg 1 9 p3 $end
$var reg 1 : p4 $end
$var reg 1 ; p5 $end
$var reg 1 < p6 $end
$var reg 1 = p7 $end
$var reg 1 > p8 $end
$var reg 1 ? p9 $end
$scope module T1 $end
$var wire 1 ) A $end
$var wire 1 4 B $end
$var wire 1 9 C $end
$var wire 1 ( Y $end
$var wire 1 @ w1 $end
$var wire 1 A w2 $end
$var wire 1 B w3 $end
$var wire 1 C w4 $end
$var wire 1 D w5 $end
$var wire 1 E w6 $end
$upscope $end
$scope module T1_2 $end
$var wire 1 - A $end
$var wire 1 . B $end
$var wire 1 / C $end
$var wire 1 0 D $end
$var wire 1 $ Y $end
$var wire 1 F w1 $end
$var wire 1 G w2 $end
$var wire 1 H w3 $end
$var wire 1 I w4 $end
$var wire 1 J w5 $end
$var wire 1 K w6 $end
$var wire 1 L w7 $end
$upscope $end
$scope module T2 $end
$var wire 1 : B $end
$var wire 1 ' Y $end
$upscope $end
$scope module T2_2 $end
$var wire 1 1 B $end
$var wire 1 2 C $end
$var wire 1 # Y $end
$var wire 1 M w1 $end
$upscope $end
$scope module T3 $end
$var wire 1 ; A $end
$var wire 1 < B $end
$var wire 1 = C $end
$var wire 1 > D $end
$var wire 1 & Y $end
$upscope $end
$scope module T3_2 $end
$var wire 1 3 B $end
$var wire 1 5 C $end
$var wire 1 6 D $end
$var wire 1 " Y $end
$upscope $end
$scope module T4 $end
$var wire 1 ? A $end
$var wire 1 * B $end
$var wire 1 + C $end
$var wire 1 , D $end
$var wire 1 % Y $end
$upscope $end
$scope module T4_2 $end
$var wire 1 7 B $end
$var wire 1 8 C $end
$var wire 1 ! Y $end
$upscope $end
$upscope $end
$enddefinitions $end
#0
$dumpvars
xM
xL
xK
xJ
xI
xH
xG
xF
0E
0D
1C
1B
1A
1@
x?
x>
x=
x<
x;
x:
09
x8
x7
x6
x5
04
x3
x2
x1
x0
x/
x.
x-
x,
x+
x*
0)
1(
x'
x&
x%
x$
x#
x"
x!
$end
#1
0(
0C
0B
19
#2
1(
1C
1B
0A
09
14
#3
0(
0C
0B
19
#4
1(
1D
1B
1A
0@
09
04
1)
#5
0B
1E
19
#6
0(
0D
1B
0E
0A
09
14
#7
1(
0B
1E
19
#10
1'
0:
#11
0'
1:
#20
1&
0>
0=
0<
0;
#21
0&
1>
#22
0>
1=
#23
1&
1>
#24
0&
0>
0=
1<
#25
1&
1>
#26
0>
1=
#27
0&
1>
#28
0>
0=
0<
1;
#29
1&
1>
#30
0>
1=
#31
0&
1>
#32
1&
0>
0=
1<
#33
0&
1>
#34
0>
1=
#35
1&
1>
#40
1%
0,
0+
0*
0?
#41
0%
1,
#42
1%
0,
1+
#43
0%
1,
#44
0,
0+
1*
#45
1,
#46
0,
1+
#47
1,
#48
1%
0,
0+
0*
1?
#49
0%
1,
#50
1%
0,
1+
#51
1,
#52
0,
0+
1*
#53
1,
#54
0,
1+
#55
1,
#60
1$
1I
1H
1G
1F
0J
0K
0L
00
0/
0.
0-
#61
0$
0I
0H
10
#62
1H
0G
00
1/
#63
0H
10
#64
1H
1G
0F
00
0/
1.
#65
0H
10
#66
1H
0G
00
1/
#67
0H
10
#68
1$
1J
1I
1K
1H
1G
1F
00
0/
0.
1-
#69
0I
0H
10
#70
1L
0J
1H
0G
00
1/
#71
0L
0H
10
#72
1J
0K
1H
1G
0F
00
0/
1.
#73
0H
10
#74
1L
0J
1H
0G
00
1/
#75
0$
0L
0H
10
#80
1#
1M
02
01
#81
12
#82
0#
0M
02
11
#83
1#
12
#90
0"
06
05
03
#91
1"
16
#92
0"
06
15
#93
1"
16
#94
06
05
13
#95
16
#96
06
15
#97
16
#100
1!
08
07
#101
0!
18
#102
1!
08
17
#103
18
