Laboratorio_03/Tabla_1_POS/tabla01.v
module tabla01();

//POS Tabla #1

reg A,B,C;
wire w1,w2,w3,w4,w5,w6,out;

	not (w1,A);
	not (w2,B);
	not (w3,C);

	or (w4,A,B,w3);
	or (w5,A,w2,w3);
	or (w6,w1,w2,C);

	and (out,w4,w5,w6);

initial begin 

	$display("A B C | Y");
	$display("---------");	
	$monitor("%b %b %b | %b", A,B,C, out);
	A=0;B=0;C=0;
	#1 C=1;
	#1 B=1;C=0;
	#1 C=1;
	#1 A=1; B=0; C=0;
	#1 C=1;
	#1 B=1;C=0;
	#1 C=1;
	#1 $finish;
end

initial 
	begin
		$dumpfile("tabla01_tb.vcd");
		$dumpvars(0,tabla01);
	end

endmodule

Laboratorio_03/Tabla_1_POS/tabla01_tb.vcd
$date
	Fri Jul 31 22:56:42 2020
$end
$version
	Icarus Verilog
$end
$timescale
	1ps
$end
$scope module tabla01 $end
$var wire 1 ! out $end
$var wire 1 " w1 $end
$var wire 1 # w2 $end
$var wire 1 $ w3 $end
$var wire 1 % w4 $end
$var wire 1 & w5 $end
$var wire 1 ' w6 $end
$var reg 1 ( A $end
$var reg 1 ) B $end
$var reg 1 * C $end
$upscope $end
$enddefinitions $end
#0
$dumpvars
0*
0)
0(
1'
1&
1%
1$
1#
1"
1!
$end
#1
0!
0%
0$
1*
#2
1!
1$
1%
0#
0*
1)
#3
0!
0&
0$
1*
#4
1!
1$
1#
1&
0"
0*
0)
1(
#5
0$
1*
#6
0!
0'
1$
0#
0*
1)
#7
1!
1'
0$
1*
