Laboratorio_04/Ejercicio_5/Alarmas.v

//Solución SOP
//gateLevel
module SOP(input wire A,B,C, output wire Y);

wire w1,w2,w3,w4,w5;
	
	not (w1,B);
	not (w2,C);
	
	and (w3,A,w1,C);
	and (w4,A,B,w2);
	and (w5,A,B,C);
	
	or (Y,w3,w4,w5);
	
endmodule

//Solución POS
//gateLevel
module POS(input wire A,B,C, output wire Y);

wire w1,w2,w3,w4,w5,w6,w7,w8;
	
	not (w1,A);
	not (w2,B);
	not (w3,C);

	or (w4,A,B,C);
	or (w5,A,B,w3);
	or (w6,A,w2,C);
	or (w7,A,w2,w3);
	or (w8,w1,B,C);
	
	and (Y,w4,w5,w6,w7,w8);
	
endmodule

//Solución Karnaug
//gateLevel
module Karnaug(input wire A,B,C, output wire Y);

wire w1,w2;

	and (w1,A,B);
	and (w2,A,C);
	
	or (Y,w1,w2);

endmodule

Laboratorio_04/Ejercicio_5/Alarmas_tb.v

module Simulacion();

	reg p1,p2,p3,p4,p5,p6,p7,p8,p9;
	wire led1,led2,led3;
	
	SOP S(p1,p2,p3,led1);
	
	POS P(p4,p5,p6,led2);
	
	Karnaug K(p7,p8,p9,led3);
	
initial begin

		$display("\n Solución SOP");
		$display("A B C | Y");
		$display("------|--");
		$monitor("%b %b %b | %b",p1,p2,p3,led1);
		
		p1=0;p2=0;p3=0;
		#1 p1=0;p2=0;p3=1;
		#1 p1=0;p2=1;p3=0;
		#1 p1=0;p2=1;p3=1;
		#1 p1=1;p2=0;p3=0;
		#1 p1=1;p2=0;p3=1;
		#1 p1=1;p2=1;p3=0;
		#1 p1=1;p2=1;p3=1;
		
	end
	
initial begin

		#10
		$display("\n Solución POS");
		$display("A B C | Y");
		$display("------|--");
		$monitor("%b %b %b | %b",p4,p5,p6,led2);
		
		p4=0;p5=0;p6=0;
		#1 p4=0;p5=0;p6=1;
		#1 p4=0;p5=1;p6=0;
		#1 p4=0;p5=1;p6=1;
		#1 p4=1;p5=0;p6=0;
		#1 p4=1;p5=0;p6=1;
		#1 p4=1;p5=1;p6=0;
		#1 p4=1;p5=1;p6=1;
		
	end
	
initial begin
		
		#20
		$display("\n Solución de Karnaug");
		$display("A B C | Y");
		$display("------|--");
		$monitor("%b %b %b | %b",p7,p8,p9,led3);
		
		p7=0;p8=0;p9=0;
		#1 p7=0;p8=0;p9=1;
		#1 p7=0;p8=1;p9=0;
		#1 p7=0;p8=1;p9=1;
		#1 p7=1;p8=0;p9=0;
		#1 p7=1;p8=0;p9=1;
		#1 p7=1;p8=1;p9=0;
		#1 p7=1;p8=1;p9=1;
	
	end
	
initial begin
		$dumpfile("Alarmas_tb.vcd");
		$dumpvars(0,Simulacion);
	
	end

initial
	#40 $finish;
endmodule

Laboratorio_04/Ejercicio_5/Alarmas_tb.vcd
$date
	Sun Aug 09 20:32:30 2020
$end
$version
	Icarus Verilog
$end
$timescale
	1ps
$end
$scope module Simulacion $end
$var wire 1 ! led3 $end
$var wire 1 " led2 $end
$var wire 1 # led1 $end
$var reg 1 $ p1 $end
$var reg 1 % p2 $end
$var reg 1 & p3 $end
$var reg 1 ' p4 $end
$var reg 1 ( p5 $end
$var reg 1 ) p6 $end
$var reg 1 * p7 $end
$var reg 1 + p8 $end
$var reg 1 , p9 $end
$scope module K $end
$var wire 1 * A $end
$var wire 1 + B $end
$var wire 1 , C $end
$var wire 1 ! Y $end
$var wire 1 - w1 $end
$var wire 1 . w2 $end
$upscope $end
$scope module P $end
$var wire 1 ' A $end
$var wire 1 ( B $end
$var wire 1 ) C $end
$var wire 1 " Y $end
$var wire 1 / w1 $end
$var wire 1 0 w2 $end
$var wire 1 1 w3 $end
$var wire 1 2 w4 $end
$var wire 1 3 w5 $end
$var wire 1 4 w6 $end
$var wire 1 5 w7 $end
$var wire 1 6 w8 $end
$upscope $end
$scope module S $end
$var wire 1 $ A $end
$var wire 1 % B $end
$var wire 1 & C $end
$var wire 1 # Y $end
$var wire 1 7 w1 $end
$var wire 1 8 w2 $end
$var wire 1 9 w3 $end
$var wire 1 : w4 $end
$var wire 1 ; w5 $end
$upscope $end
$upscope $end
$enddefinitions $end
#0
$dumpvars
0;
0:
09
18
17
x6
x5
x4
x3
x2
x1
x0
x/
x.
x-
x,
x+
x*
x)
x(
x'
0&
0%
0$
0#
x"
x!
$end
#1
08
1&
#2
18
07
0&
1%
#3
08
1&
#4
18
17
0&
0%
1$
#5
1#
08
19
1&
#6
1:
1#
18
09
07
0&
1%
#7
0:
08
1;
1&
#10
0"
13
14
15
11
10
16
1/
02
0)
0(
0'
#11
0"
03
01
12
1)
#12
11
04
00
13
0)
1(
#13
0"
05
01
14
1)
#14
11
10
06
0/
15
0)
0(
1'
#15
1"
01
16
1)
#16
11
00
0)
1(
#17
01
1)
#20
0!
0-
0.
0,
0+
0*
#21
1,
#22
0,
1+
#23
1,
#24
0,
0+
1*
#25
1!
1.
1,
#26
0.
1-
0,
1+
#27
1.
1,
