Laboratorio_08/Ejercicio_1/Module.v
module ejercicio01 (input wire clk, enabled, reset,load, input wire [11:0]d , 
					output reg [11:0]q);
		
	initial q=0;
	
	always @ (posedge clk or posedge enabled or posedge load)
	if (reset==1) q<=0;
	
	else if (enabled==1)
			begin	
				if (load==1)
					begin 
					q<= d;
					q<= q + 1'b1;
					end
				else q<= q+1'b1;
			end
	else q<=q;
	
endmodule

Laboratorio_08/Ejercicio_1/Module_tb.v
module testbench();

reg clk,reset, enabled,load;
reg [11:0] d;
wire [11:0]q;

ejercicio01 U1(clk,enabled,reset,load,d,q);

initial begin

	$display("clk | reset | enabled | load |    d    |  q  |");
	$display("----|-------|---------|------|---------|-----|");
	$monitor("%b   |   %b   |    %b    |   %b  |  %d   |%d |",clk,reset,enabled,load,d,q);
	
	clk=0;reset=0;enabled=1;load=0;d=100;
	#2
	#1 enabled=0;
	#6
	#1 enabled=1;load =1;
	#4 
	#1 reset=1;
	#1 reset=0; enabled=1;
	#6
	#1 reset=1;
	#1 reset=0;
	#1 $finish;
	
	
end

always 
		#1 clk= ~clk;
		
initial begin

	$dumpfile("Module_tb.vcd");
	$dumpvars(0,testbench);

end
		
endmodule

Laboratorio_08/Ejercicio_1/Module_tb.vcd
$date
	Sat Oct 24 19:46:16 2020
$end
$version
	Icarus Verilog
$end
$timescale
	1ps
$end
$scope module testbench $end
$var wire 12 ! q [11:0] $end
$var reg 1 " clk $end
$var reg 12 # d [11:0] $end
$var reg 1 $ enabled $end
$var reg 1 % load $end
$var reg 1 & reset $end
$scope module U1 $end
$var wire 1 " clk $end
$var wire 12 ' d [11:0] $end
$var wire 1 $ enabled $end
$var wire 1 % load $end
$var wire 1 & reset $end
$var reg 12 ( q [11:0] $end
$upscope $end
$upscope $end
$enddefinitions $end
#0
$dumpvars
b1 (
b1100100 '
0&
0%
1$
b1100100 #
0"
b1 !
$end
#1
b10 !
b10 (
1"
#2
0"
#3
1"
0$
#4
0"
#5
1"
#6
0"
#7
1"
#8
0"
#9
1"
#10
b11 !
b11 (
0"
1%
1$
#11
b100 !
b100 (
1"
#12
0"
#13
b101 !
b101 (
1"
#14
0"
#15
b0 !
b0 (
1"
1&
#16
0"
0&
#17
b1 !
b1 (
1"
#18
0"
#19
b10 !
b10 (
1"
#20
0"
#21
b11 !
b11 (
1"
#22
0"
#23
b0 !
b0 (
1"
1&
#24
0"
0&
#25
b1 !
b1 (
1"
