Laboratorio_9/Ejercicio_03/FFJK.v
module FFJK(input clk, enable,reset,J,K, output reg Q);

	always @ (posedge clk or posedge reset or posedge enable) 

		if (reset==0)
			begin
				if(enable==1) 
					begin
						if (J==0) 
							begin
								if (K==0)begin
									Q<=Q;
									end
								else if (K==1)begin
									Q<=0;
									end
							end
						else if (J==1)begin
								if (K==0)begin
									Q<=1;
									end
									else if (K==1)begin
										Q<= ~Q;
										end
							end
						
					end
				else if (enable==0)begin
						Q<=Q;
					end
			end
		else if (reset==1)
			begin
		
				Q<=1'b0;
				
			end



endmodule

Laboratorio_9/Ejercicio_03/FFJK_tb.v
module testbench();

reg clk,reset,enabled,J,K;
wire Q;

FFJK U1(clk,enabled,reset,J,K,Q);

initial begin

	$display("Ejercicio 3");
	$display("clk | Reset | Enabled | J | K | Q ");
	$monitor("%b   |   %b   |    %b    | %b | %b | %b",clk,reset,enabled,J,K,Q);
	
	clk=0;reset=0; enabled=1; J=0;K=1;
	#1 K=0;
	#1 J=1;K=0;
	#2
	#1 reset=1;
	#1 reset=0;
	#1 J=1;K=1;
	#4
	#1 enabled =1;
	#2 
	#1 $finish;
	
end

always
	#1 clk= ~clk;
	initial begin
		
		$dumpfile("FFJK_tb.vcd");
		$dumpvars(0,testbench);
	
	end
	

endmodule

Laboratorio_9/Ejercicio_03/FFJK_tb.vcd
$date
	Sat Oct 31 23:34:07 2020
$end
$version
	Icarus Verilog
$end
$timescale
	1ps
$end
$scope module testbench $end
$var wire 1 ! Q $end
$var reg 1 " J $end
$var reg 1 # K $end
$var reg 1 $ clk $end
$var reg 1 % enabled $end
$var reg 1 & reset $end
$scope module U1 $end
$var wire 1 " J $end
$var wire 1 # K $end
$var wire 1 $ clk $end
$var wire 1 % enable $end
$var wire 1 & reset $end
$var reg 1 ! Q $end
$upscope $end
$upscope $end
$enddefinitions $end
#0
$dumpvars
0&
1%
0$
1#
0"
0!
$end
#1
1$
0#
#2
0$
1"
#3
1!
1$
#4
0$
#5
0!
1$
1&
#6
0$
0&
#7
1!
1$
1#
#8
0$
#9
0!
1$
#10
0$
#11
1!
1$
#12
0$
#13
0!
1$
#14
0$
#15
1!
1$
