Laboratorio_06/Ejercicio_6/FSM_MOORE/FSM2.v
module FSM_Moore (input clk, reset, a, output y1,y2,y3);

reg [1:0] state, nextstate;

parameter e0 = 3'b000;
parameter e1 = 3'b001;
parameter e2 = 3'b010;
parameter e3 = 3'b011;
parameter e4 = 3'b100;
parameter e5 = 3'b101;
parameter e6 = 3'b110;
parameter e7 = 3'b111;

always@(posedge clk or posedge reset)
	if (reset==1)
		state <= e0;
	else
		state <= nextstate;

always@ (*)
	case(state)
		e0: if(a==1) nextstate=e1;
		else nextstate =e7;

		
		e1: if(a==1) nextstate=e2;
		else nextstate =e0;
		
		e2: if (a==1) nextstate =e3;
		else nextstate= e1;
		
		e3: if(a==1) nextstate=e4;
		else nextstate =e2;
		
		e4: if(a==1) nextstate=e5;
		else nextstate =e3;
		
		e5: if (a==1) nextstate =e6;
		else nextstate= e4;
		
		e6: if(a==1) nextstate=e7;
		else nextstate =e5;
		
		e7: if(a==1) nextstate=e0;
		else nextstate =e6;
		
		default nextstate = e0;
	endcase
		
		assign y1 =(state== e4) | (state==e5) | (state==e6) | (state==e7);
		assign y2 =(state == e2) | (state==e3) | (state==e4) | (state==e5);
		assign y3 =(state == e1) | (state==e2) | (state==e5) | (state==e6);


endmodule

Laboratorio_06/Ejercicio_6/FSM_MOORE/FSM2_tb.v
module testbench();

reg clk,reset,a;
wire y1,y2,y3;

FSM_Moore U2(clk, reset,a,y1,y2,y3);

initial begin 
	$display("clk reset A | Y1 Y2 Y3");
	$display("----------------|--");
	$monitor("%b    %b   %b  | %b %b %b ",clk,reset,a,y1,y2,y3);
	
	clk=0;
	reset=0;
	a=1;
	#20
	#1 reset =1;
	#1 reset =0;
	#2 reset =1;
	#2 reset =0;
	a=0;
	#10
	#1 reset =1;
	#1 reset =0;
	#2 reset =1;
	#2 reset =0;
	#2 $finish;
	
end

	always 
		#1 clk= ~clk;

initial begin
		
		$dumpfile("FSM2_tb.vcd");
		$dumpvars(0,testbench);
	
	end
	
endmodule

Laboratorio_06/Ejercicio_6/FSM_MOORE/FSM2_tb.vcd
$date
	Sun Sep 06 16:03:52 2020
$end
$version
	Icarus Verilog
$end
$timescale
	1ps
$end
$scope module testbench $end
$var wire 1 ! y3 $end
$var wire 1 " y2 $end
$var wire 1 # y1 $end
$var reg 1 $ a $end
$var reg 1 % clk $end
$var reg 1 & reset $end
$scope module U2 $end
$var wire 1 $ a $end
$var wire 1 % clk $end
$var wire 1 & reset $end
$var wire 1 # y1 $end
$var wire 1 " y2 $end
$var wire 1 ! y3 $end
$var reg 2 ' nextstate [1:0] $end
$var reg 2 ( state [1:0] $end
$upscope $end
$upscope $end
$enddefinitions $end
#0
$dumpvars
bx (
b0 '
0&
0%
1$
0#
x"
x!
$end
#1
0"
0!
b1 '
b0 (
1%
#2
0%
#3
1!
b10 '
b1 (
1%
#4
0%
#5
1"
b11 '
b10 (
1%
#6
0%
#7
0!
b0 '
b11 (
1%
#8
0%
#9
0"
b1 '
b0 (
1%
#10
0%
#11
1!
b10 '
b1 (
1%
#12
0%
#13
1"
b11 '
b10 (
1%
#14
0%
#15
0!
b0 '
b11 (
1%
#16
0%
#17
0"
b1 '
b0 (
1%
#18
0%
#19
1!
b10 '
b1 (
1%
#20
0%
#21
0!
b1 '
b0 (
1%
1&
#22
0%
0&
#23
1!
b10 '
b1 (
1%
#24
0!
b1 '
b0 (
0%
1&
#25
1%
#26
b11 '
0%
0$
0&
#27
1"
b10 '
b11 (
1%
#28
0%
#29
1!
b1 '
b10 (
1%
#30
0%
#31
0"
b0 '
b1 (
1%
#32
0%
#33
0!
b11 '
b0 (
1%
#34
0%
#35
1"
b10 '
b11 (
1%
#36
0%
#37
0"
b11 '
b0 (
1%
1&
#38
0%
0&
#39
1"
b10 '
b11 (
1%
#40
0"
b11 '
b0 (
0%
1&
#41
1%
#42
0%
0&
#43
1"
b10 '
b11 (
1%
