Laboratorio_03/Tabla_2_SOP/tabla02_2.v
module tabla02_2();

//SOP tabla 2

reg A,B,C;
wire w1,w2,w3,w4,w5,w6,out;

	not NOTA(w1,A);
	not NOTB(w2,B);
	not NOTC(w3,C);
	
	and AND1(w4,w1,w2,C);
	and AND2(w5,A,B,w3);
	and AND3(w6,A,B,C);
	
	or OUT(out,w4,w5,w6);
	
initial begin;

	$display("A B C | Y");
	$display("---------");
	$monitor("%b %b %b | %b", A, B, C, out);
	A=0;B=0;C=0;
	#1 C=1;
	#1 B=1;C=0;
	#1 C=1;
	#1 A=1;B=0;C=0;
	#1 C=1;
	#1 B=1;C=0;
	#1 C=1;
	#1 $finish;
end

initial 
	begin
		$dumpfile("tabla02_2_tb.vcd");
		$dumpvars(0,tabla02_2);
	end
endmodule

Laboratorio_03/Tabla_2_SOP/tabla02_2_tb.vcd
$date
	Fri Jul 31 23:22:27 2020
$end
$version
	Icarus Verilog
$end
$timescale
	1ps
$end
$scope module tabla02_2 $end
$var wire 1 ! out $end
$var wire 1 " w1 $end
$var wire 1 # w2 $end
$var wire 1 $ w3 $end
$var wire 1 % w4 $end
$var wire 1 & w5 $end
$var wire 1 ' w6 $end
$var reg 1 ( A $end
$var reg 1 ) B $end
$var reg 1 * C $end
$upscope $end
$enddefinitions $end
#0
$dumpvars
0*
0)
0(
0'
0&
0%
1$
1#
1"
0!
$end
#1
1!
1%
0$
1*
#2
0!
0%
1$
0#
0*
1)
#3
0$
1*
#4
1$
1#
0"
0*
0)
1(
#5
0$
1*
#6
1!
1&
1$
0#
0*
1)
#7
0&
1'
0$
1*
