Proyecto/Codigo/Proyecto.v
module ffd (input clk, reset,D, output reg Q);

	always @ (posedge clk or posedge reset) 
	begin
		if (reset==1)
			Q<=1'b0;
		else
			Q<=D;
	end
endmodule
 
module elevador (input clk, reset, A, B, output wire Y1,Y2,C);
 
	wire S1,S2,S1_F,S2_F,P1,P1_F,P2,P2_F,P3,P3_F,P4,P4_F;
	
	
	
	ffd U1(clk,reset,S1,S1_F);
	ffd U2(clk,reset,S2,S2_F);
	
	ffd U3(clk,reset,P1,P1_F);
	ffd U4(clk,reset,P2,P2_F);
	ffd U5(clk,reset,P3,P3_F);
	ffd U6(clk,reset,P4,P4_F);
	
	assign S1_F =(S2 & A & ~B & ~P1)|(S2 & A & ~B & ~P4)|(S1 & P1 & P4)|(S1 & S2)|(S1 & ~B)|(S1 & A); 
	assign S2_F =(S1 & ~S2 & ~A & B & ~P1) | (S1 & ~S2 & ~A & B & ~P4) | (~S1 & A & B & ~P1) | (~S1 & A & B & ~P4) 
				| (~S2 & A & ~B & ~P1) | (~S2 & A & ~B & ~P4) | (S2 & P1 & P4) | (S2 & ~A & ~B) | (S1 & S2 & ~B);
	
	assign P1_F =(P2 & P3 & P4) | (P1 & ~P3);
	assign P2_F =(~P2 & P3 & P4) | (P2 & ~P3) | (P2 & ~P4);
	assign P3_F =(~P1 & P3 & ~P4) | (~P3 & P4);
	assign P4_F =(~P1 & P3 & ~P4) | (~P3 & ~P4);

	assign Y1 = (~S1 & S2) | (S1 & ~S2);
	assign Y2 = (~S2);
	assign C = (P1 & P3); 
	
endmodule

Proyecto/Codigo/Proyecto_tb.v
module testbench();

	reg A,B,clk,reset; 
	wire Y1,Y2,C;
	
	elevador F1(clk,reset,A,B,Y1,Y2,C);
	
	initial begin 
		
		$display ("Proyecto 1: Electronica digital 1");	
		$display ("-----------El Elevador-----------");
		$display ("Piso | A B | C | CLK | Reset |");
		$monitor (" %b %b  | %b %b | %b |  %b  |   %b   |", Y1,Y2,A,B,C,clk,reset);
		
		reset =0; A=0; B=0;clk=0;
		#2
		#3 A=1;
		#3 B=1;
		#1 reset =1;
		#1 reset =0;
		#2 B=0;
		#2 A=0;
		#3 A=1;
		#3 B=1;
		#2 B=0;
		#2 A=0;
		#5 A=1;
		#1 A=0;
		#5 B=1;
		#1 B=0;
		#1 reset =1;
		#1 reset =0;
		#1 $finish;
	end
	
	always 
	#1 clk = ~clk;
	
initial begin
		
		$dumpfile("Proyecto_tb.vcd");
		$dumpvars(0,testbench);
	
	end
	
endmodule

Proyecto/Codigo/Proyecto_tb.vcd
$date
	Sat Oct 17 21:25:55 2020
$end
$version
	Icarus Verilog
$end
$timescale
	1ps
$end
$scope module testbench $end
$var wire 1 ! Y2 $end
$var wire 1 " Y1 $end
$var wire 1 # C $end
$var reg 1 $ A $end
$var reg 1 % B $end
$var reg 1 & clk $end
$var reg 1 ' reset $end
$scope module F1 $end
$var wire 1 $ A $end
$var wire 1 % B $end
$var wire 1 # C $end
$var wire 1 ( P1 $end
$var wire 1 ) P1_F $end
$var wire 1 * P2 $end
$var wire 1 + P2_F $end
$var wire 1 , P3 $end
$var wire 1 - P3_F $end
$var wire 1 . P4 $end
$var wire 1 / P4_F $end
$var wire 1 0 S1 $end
$var wire 1 1 S1_F $end
$var wire 1 2 S2 $end
$var wire 1 3 S2_F $end
$var wire 1 " Y1 $end
$var wire 1 ! Y2 $end
$var wire 1 & clk $end
$var wire 1 ' reset $end
$scope module U1 $end
$var wire 1 0 D $end
$var wire 1 & clk $end
$var wire 1 ' reset $end
$var reg 1 4 Q $end
$upscope $end
$scope module U2 $end
$var wire 1 2 D $end
$var wire 1 & clk $end
$var wire 1 ' reset $end
$var reg 1 5 Q $end
$upscope $end
$scope module U3 $end
$var wire 1 ( D $end
$var wire 1 & clk $end
$var wire 1 ' reset $end
$var reg 1 6 Q $end
$upscope $end
$scope module U4 $end
$var wire 1 * D $end
$var wire 1 & clk $end
$var wire 1 ' reset $end
$var reg 1 7 Q $end
$upscope $end
$scope module U5 $end
$var wire 1 , D $end
$var wire 1 & clk $end
$var wire 1 ' reset $end
$var reg 1 8 Q $end
$upscope $end
$scope module U6 $end
$var wire 1 . D $end
$var wire 1 & clk $end
$var wire 1 ' reset $end
$var reg 1 9 Q $end
$upscope $end
$upscope $end
$upscope $end
$enddefinitions $end
#0
$dumpvars
x9
x8
x7
x6
x5
x4
x3
z2
x1
z0
x/
z.
x-
z,
x+
z*
x)
z(
0'
0&
0%
0$
x#
x"
z!
$end
#1
z4
z5
z6
z7
z8
z9
1&
#2
0&
#3
1&
#4
0&
#5
1&
1$
#6
0&
#7
1&
#8
0&
1%
#9
04
05
06
07
08
09
1&
1'
#10
0&
0'
#11
z9
z8
z7
z6
z5
z4
1&
#12
0&
0%
#13
1&
#14
0&
0$
#15
1&
#16
0&
#17
1&
1$
#18
0&
#19
1&
#20
0&
1%
#21
1&
#22
0&
0%
#23
1&
#24
0&
0$
#25
1&
#26
0&
#27
1&
#28
0&
#29
1&
1$
#30
0&
0$
#31
1&
#32
0&
#33
1&
#34
0&
#35
1&
1%
#36
0&
0%
#37
04
05
06
07
08
09
1&
1'
#38
0&
0'
#39
z9
z8
z7
z6
z5
z4
1&
